ecg_quality/ECGQualityChecker.py
ecg_quality/__init__.py
ecg_quality/model.py
ecg_quality/tf_model.py
ecg_quality/utils.py
ecg_quality/models/CNN2s.h5
ecg_quality/models/CNN5s.h5
ecg_quality/models/LSTM2s.h5
ecg_quality/models/OSCNN2s.h5
ecg_quality/models/__init__.py
ecg_quality-0.2.0.dist-info/LICENSE
ecg_quality-0.2.0.dist-info/METADATA
ecg_quality-0.2.0.dist-info/WHEEL
ecg_quality-0.2.0.dist-info/top_level.txt
ecg_quality-0.2.0.dist-info/RECORD
