Metadata-Version: 2.1
Name: ecg-quality
Version: 0.2.0
Summary: Library that classifies quality of ECG signal using deep learning methods
Home-page: https://github.com/koledjoz/ecg_quality
Download-URL: https://github.com/koledjoz/ecg_quality/releases/tag/v0.2.0
Author: Jozef Koleda
Author-email: koledjoz@cvut.cz
License: gpl-3.0
Keywords: ECG,quality,classification,deep learning
License-File: LICENSE
Requires-Dist: tensorflow
Requires-Dist: numpy
Requires-Dist: neurokit2
